bmipy/__init__.py
bmipy/_version.py
bmipy/bmi.py
bmipy/cmd.py
bmipy/py.typed
bmipy-2.0.1.dist-info/LICENSE
bmipy-2.0.1.dist-info/METADATA
bmipy-2.0.1.dist-info/WHEEL
bmipy-2.0.1.dist-info/entry_points.txt
bmipy-2.0.1.dist-info/top_level.txt
bmipy-2.0.1.dist-info/RECORD
