Metadata-Version: 2.1
Name: bmipy
Version: 2.0.1
Summary: Basic Model Interface for Python
Author-email: Eric Hutton <huttone@colorado.edu>
License: MIT
Project-URL: Documentation, https://bmi.readthedocs.io
Project-URL: Source, https://github.com/csdms/bmi-python
Keywords: BMI,Basic Model Interface
Classifier: Development Status :: 4 - Beta
Classifier: Intended Audience :: Science/Research
Classifier: License :: OSI Approved :: MIT License
Classifier: Operating System :: OS Independent
Classifier: Programming Language :: Python :: 3 :: Only
Classifier: Programming Language :: Python :: 3.9
Classifier: Programming Language :: Python :: 3.10
Classifier: Programming Language :: Python :: 3.11
Classifier: Programming Language :: Python :: 3.12
Classifier: Programming Language :: Python :: Implementation :: CPython
Classifier: Topic :: Scientific/Engineering :: Hydrology
Classifier: Topic :: Scientific/Engineering :: Physics
Requires-Python: >=3.9
License-File: LICENSE
Requires-Dist: black
Requires-Dist: click
Requires-Dist: jinja2
Requires-Dist: numpy
